summarify/__init__.py
summarify/parser.py
summarify/py.typed
summarify/summary.py
summarify-0.1.0.dist-info/LICENSE
summarify-0.1.0.dist-info/METADATA
summarify-0.1.0.dist-info/WHEEL
summarify-0.1.0.dist-info/RECORD
