Metadata-Version: 2.1
Name: summarify
Version: 0.1.0
Summary: Get title and description from a Web page
Home-page: https://github.com/bfontaine/summarify
Author: Baptiste Fontaine
Author-email: b@ptistefontaine.fr
Requires-Python: >=3.8,<4.0
Classifier: Intended Audience :: Developers
Classifier: License :: OSI Approved :: MIT License
Classifier: Operating System :: OS Independent
Classifier: Programming Language :: Python :: 3
Classifier: Programming Language :: Python :: 3.8
Classifier: Programming Language :: Python :: 3.9
Classifier: Programming Language :: Python :: 3.10
Classifier: Programming Language :: Python :: 3.11
Classifier: Programming Language :: Python :: 3.12
Requires-Dist: beautifulsoup4 (>=4.9.3,<5.0.0)
Requires-Dist: requests (>=2.28.2,<3.0.0)
